ecst/__init__.py
ecst/__main__.py
ecst-0.0.12.dist-info/METADATA
ecst-0.0.12.dist-info/WHEEL
ecst-0.0.12.dist-info/RECORD
