Metadata-Version: 2.3
Name: ecst
Version: 0.0.12
Summary: Create local tunnels and sessions to AWS ECS services running in a VPC.
Project-URL: Homepage, https://github.com/mikefrancis/ecstunnel
Project-URL: Bug Tracker, https://github.com/mikefrancis/ecstunnel/issues
Author-email: Mike Francis <mikeffrancis@gmail.com>
Classifier: License :: OSI Approved :: MIT License
Classifier: Operating System :: OS Independent
Classifier: Programming Language :: Python :: 3
Requires-Python: >=3.7
Requires-Dist: boto3
